dota2gsi/__init__.py
dota2gsi/server_log_parser.py
dota2gsi-0.1.dist-info/LICENSE
dota2gsi-0.1.dist-info/METADATA
dota2gsi-0.1.dist-info/WHEEL
dota2gsi-0.1.dist-info/top_level.txt
dota2gsi-0.1.dist-info/RECORD
