Metadata-Version: 2.1
Name: dota2gsi
Version: 0.1
Summary: DotA 2 GSI Interface
Home-page: https://gitlab.com/avalonparton/dota-gsi
Author: Avalon Parton
Author-email: avalonlee@gmail.com
License: MIT
Platform: UNKNOWN
